{
  "clones_summary": {
    "Clone_1": "SNV13",
    "Clone_2": ["SNV13", "SNV3"],
    "Clone_3": ["SNV13", "SNV3", "SNV8"],
    "Clone_4": ["SNV13", "SNV3", "SNV8", "SNV5"],
    "Clone_5": ["SNV13", "SNV3", "SNV8", "SNV5", "SNV7"],
    "Clone_6": ["SNV13", "SNV3", "SNV8", "SNV5", "SNV7", "SNV10"],
    "Clone_7": ["SNV13", "SNV3", "SNV8", "SNV5", "SNV7", "SNV10", "SNV12"],
    "Clone_8": ["SNV13", "SNV3", "SNV8", "SNV5", "SNV7", "SNV10", "SNV12", "SNV6"],
    "Clone_9": ["SNV13", "SNV3", "SNV8", "SNV5", "SNV7", "SNV10", "SNV12", "SNV6", "SNV2"],
    "Clone_10": ["SNV13", "SNV3", "SNV8", "SNV5", "SNV7", "SNV10", "SNV12", "SNV6", "SNV2", "SNV15"],
    "Clone_11": ["SNV13", "SNV3", "SNV8", "SNV5", "SNV7", "SNV10", "SNV12", "SNV6", "SNV2", "SNV15", "SNV18"],
    "Clone_12": ["SNV13", "SNV3", "SNV8", "SNV5", "SNV7", "SNV10", "SNV12", "SNV6", "SNV2", "SNV15", "SNV18", "SNV17"],
    "Clone_13": ["SNV13", "SNV3", "SNV8", "SNV5", "SNV7", "SNV10", "SNV12", "SNV6", "SNV2", "SNV15", "SNV18", "SNV17", "SNV4"],
    "Clone_14": ["SNV13", "SNV3", "SNV8", "SNV5", "SNV7", "SNV10", "SNV12", "SNV6", "SNV2", "SNV15", "SNV18", "SNV17", "SNV4", "SNV14"],
    "Clone_15": ["SNV13", "SNV3", "SNV8", "SNV5", "SNV7", "SNV10", "SNV12", "SNV6", "SNV2", "SNV15", "SNV18", "SNV17", "SNV4", "SNV14", "SNV9"],
    "Clone_16": ["SNV13", "SNV3", "SNV8", "SNV5", "SNV7", "SNV10", "SNV12", "SNV6", "SNV2", "SNV15", "SNV18", "SNV17", "SNV4", "SNV14", "SNV9", "SNV16"],
    "Clone_17": ["SNV13", "SNV3", "SNV8", "SNV5", "SNV7", "SNV10", "SNV12", "SNV6", "SNV2", "SNV15", "SNV18", "SNV17", "SNV4", "SNV14", "SNV9", "SNV16", "SNV11"],
    "Clone_18": ["SNV13", "SNV3", "SNV8", "SNV5", "SNV7", "SNV10", "SNV12", "SNV6", "SNV2", "SNV15", "SNV18", "SNV17", "SNV4", "SNV14", "SNV9", "SNV16", "SNV11", "SNV1"],
    "Clone_19": ["SNV13", "SNV3", "SNV8", "SNV5", "SNV7", "SNV10", "SNV12", "SNV6", "SNV2", "SNV15", "SNV18", "SNV17", "SNV4", "SNV14", "SNV9", "SNV16", "SNV11", "SNV23"],
    "Clone_20": ["SNV13", "SNV3", "SNV8", "SNV5", "SNV7", "SNV10", "SNV12", "SNV6", "SNV2", "SNV15", "SNV18", "SNV17", "SNV4", "SNV14", "SNV9", "SNV16", "SNV11", "SNV23", "SNV29"],
    "Clone_21": ["SNV13", "SNV3", "SNV8", "SNV5", "SNV7", "SNV10", "SNV12", "SNV6", "SNV2", "SNV15", "SNV18", "SNV17", "SNV4", "SNV14", "SNV9", "SNV16", "SNV11", "SNV23", "SNV29", "SNV21"],
    "Clone_22": ["SNV13", "SNV3", "SNV8", "SNV5", "SNV7", "SNV10", "SNV12", "SNV6", "SNV2", "SNV15", "SNV18", "SNV17", "SNV4", "SNV14", "SNV9", "SNV16", "SNV11", "SNV23", "SNV29", "SNV21", "SNV22"],
    "Clone_23": ["SNV13", "SNV3", "SNV8", "SNV5", "SNV7", "SNV10", "SNV12", "SNV6", "SNV2", "SNV15", "SNV18", "SNV17", "SNV4", "SNV14", "SNV9", "SNV16", "SNV11", "SNV23", "SNV29", "SNV21", "SNV22", "SNV25"],
    "Clone_24": ["SNV13", "SNV3", "SNV8", "SNV5", "SNV7", "SNV10", "SNV12", "SNV6", "SNV2", "SNV15", "SNV18", "SNV17", "SNV4", "SNV14", "SNV9", "SNV16", "SNV11", "SNV23", "SNV29", "SNV21", "SNV22", "SNV25", "SNV20"],
    "Clone_25": ["SNV13", "SNV3", "SNV8", "SNV5", "SNV7", "SNV10", "SNV12", "SNV6", "SNV2", "SNV15", "SNV18", "SNV17", "SNV4", "SNV14", "SNV9", "SNV16", "SNV11", "SNV23", "SNV29", "SNV21", "SNV22", "SNV25", "SNV20", "SNV30"],
    "Clone_26": ["SNV13", "SNV3", "SNV8", "SNV5", "SNV7", "SNV10", "SNV12", "SNV6", "SNV2", "SNV15", "SNV18", "SNV17", "SNV4", "SNV14", "SNV9", "SNV16", "SNV11", "SNV23", "SNV29", "SNV21", "SNV22", "SNV25", "SNV20", "SNV30", "SNV26"],
    "Clone_27": ["SNV13", "SNV3", "SNV8", "SNV5", "SNV7", "SNV10", "SNV12", "SNV6", "SNV2", "SNV15", "SNV18", "SNV17", "SNV4", "SNV14", "SNV9", "SNV16", "SNV11", "SNV23", "SNV29", "SNV21", "SNV22", "SNV25", "SNV20", "SNV30", "SNV26", "SNV27"],
    "Clone_28": ["SNV13", "SNV3", "SNV8", "SNV5", "SNV7", "SNV10", "SNV12", "SNV6", "SNV2", "SNV15", "SNV18", "SNV17", "SNV4", "SNV14", "SNV9", "SNV16", "SNV11", "SNV23", "SNV29", "SNV21", "SNV22", "SNV25", "SNV20", "SNV30", "SNV26", "SNV27", "SNV31"],
    "Clone_29": ["SNV13", "SNV3", "SNV8", "SNV5", "SNV7", "SNV10", "SNV12", "SNV6", "SNV2", "SNV15", "SNV18", "SNV17", "SNV4", "SNV14", "SNV9", "SNV16", "SNV11", "SNV23", "SNV29", "SNV21", "SNV22", "SNV25", "SNV20", "SNV30", "SNV26", "SNV27", "SNV31", "SNV24"],
    "Clone_30": ["SNV13", "SNV3", "SNV8", "SNV5", "SNV7", "SNV10", "SNV12", "SNV6", "SNV2", "SNV15", "SNV18", "SNV17", "SNV4", "SNV14", "SNV9", "SNV16", "SNV11", "SNV19"],
    "Clone_31": ["SNV13", "SNV3", "SNV8", "SNV5", "SNV7", "SNV10", "SNV12", "SNV6", "SNV2", "SNV15", "SNV18", "SNV17", "SNV4", "SNV14", "SNV9", "SNV16", "SNV11", "SNV23", "SNV29", "SNV21", "SNV22", "SNV25", "SNV20", "SNV30", "SNV26", "SNV27", "SNV31", "SNV24", "SNV28"],
    "Clone_32": ["SNV13", "SNV3", "SNV8", "SNV5", "SNV7", "SNV10", "SNV12", "SNV6", "SNV2", "SNV15", "SNV18", "SNV17", "SNV4", "SNV14", "SNV9", "SNV16", "SNV11", "SNV23", "SNV29", "SNV21", "SNV22", "SNV25", "SNV20", "SNV30", "SNV26", "SNV27", "SNV31", "SNV24", "SNV0"]
  }
}
